README
setup.py
PySkytap.egg-info/PKG-INFO
PySkytap.egg-info/SOURCES.txt
PySkytap.egg-info/dependency_links.txt
PySkytap.egg-info/not-zip-safe
PySkytap.egg-info/top_level.txt
pyskytap/__init__.py
pyskytap/pysky_configuration.py
pyskytap/pysky_psexception.py
pyskytap/pysky_skytap.py
pyskytap/pysky_vm.py