Metadata-Version: 1.0
Name: PySkytap
Version: 0.1
Summary: Python Skytap Library
Home-page: http://github.com/dman776/pyskytap
Author: Darryl Quinn
Author-email: dman776@gmail.com
License: MIT
Platform: UNKNOWN
